LICENSE
README.md
setup.cfg
setup.py
yonde/__init__.py
yonde/__main__.py
yonde/__version__.py
yonde/main.py
yonde.egg-info/PKG-INFO
yonde.egg-info/SOURCES.txt
yonde.egg-info/dependency_links.txt
yonde.egg-info/entry_points.txt
yonde.egg-info/requires.txt
yonde.egg-info/top_level.txt
yonde/color/__init__.py
yonde/color/color.py
yonde/downloader/__init__.py
yonde/downloader/downloader.py
yonde/exceptions/__init__.py
yonde/exceptions/exceptions.py
yonde/extractors/__init__.py
yonde/extractors/brmangas_com.py
yonde/extractors/elitemangas_com.py
yonde/extractors/goldenmangas_top.py
yonde/extractors/leitor_net.py
yonde/extractors/mangahost4_com.py
yonde/extractors/mangatube_site.py
yonde/extractors/mangayabu_top.py
yonde/extractors/muitomanga_com.py
yonde/extractors/unionmangas_top.py
yonde/extractors/yesmangas1_com.py
yonde/images/__init__.py
yonde/images/images.py
yonde/main_class/__init__.py
yonde/main_class/main_extractor.py
yonde/session/__init__.py
yonde/session/session.py