Metadata-Version: 2.1
Name: yonde
Version: 0.2.1
Summary: Mangá downloader (para leitura offline) voltado para sites e scans brasileiros.
Home-page: https://github.com/yonde-manga/yonde
Author: yanhuishi
Author-email: contatoyonde@protonmail.com
License: UNKNOWN
Download-URL: https://github.com/yonde-manga/yonde/archive/refs/tags/v0.2.1.tar.gz
Keywords: manga,downloader,pdf
Platform: UNKNOWN
Classifier: Development Status :: 4 - Beta
Classifier: Programming Language :: Python :: 3.7
Classifier: Programming Language :: Python :: 3.8
Classifier: Programming Language :: Python :: 3.9
Classifier: Operating System :: OS Independent
Requires-Python: >=3.7
License-File: LICENSE
